AutoFetcher/AllExceptions.py
AutoFetcher/DutCacher.py
AutoFetcher/DutFetcher.py
AutoFetcher/DutFilters.py
AutoFetcher/DutGrabber.py
AutoFetcher/Exception.py
AutoFetcher/TopologyFetcher.py
AutoFetcher/__init__.py
AutoFetcher/AsyncCacher/Consumer.py
AutoFetcher/AsyncCacher/Producer.py
AutoFetcher/AsyncCacher/__init__.py
AutoFetcher/TopoFetcher/Parser.py
AutoFetcher/TopoFetcher/Plotter.py
AutoFetcher/TopoFetcher/Processor.py
AutoFetcher/TopoFetcher/__init__.py
afad-1.0.0.dist-info/METADATA
afad-1.0.0.dist-info/WHEEL
afad-1.0.0.dist-info/top_level.txt
afad-1.0.0.dist-info/RECORD
