Metadata-Version: 2.4
Name: AFAD
Version: 1.0.0
Summary: Nothing but a human leveraging the power of threads to save time. See the below diagram and try to get it.
Author: Henil Rakeshbhai Mistry
Author-email: henil@arista.com
Requires-Dist: pika>=1.3.2
Requires-Dist: fabric>=3.2.2
Requires-Dist: packaging>=25.0
Requires-Dist: pyeapi>=1.0.4
Dynamic: author
Dynamic: author-email
Dynamic: description
Dynamic: description-content-type
Dynamic: requires-dist
Dynamic: summary
